{
  "$schema": "../security-control.schema.json",
  "ControlID": "ISO27001-2022_A.5.14",
  "Category": "Organizational Controls",
  "Name": "Information transfer",
  "Description": "Information transfer rules, procedures, or agreements shall be in place for all types of transfer facilities within the organization and between the organization and other parties.",
  "Publisher": "ISO/IEC",
  "Framework": "ISO 27001:2022",
  "AdditionalInfo": {
    "Edition": "3",
    "PublishDate": "2022-10"
  }
}
